Elasticsearch_to_GCS_Connector/__init__.py
Elasticsearch_to_GCS_Connector/main.py
Elasticsearch_to_GCS_Connector-0.0.dist-info/METADATA
Elasticsearch_to_GCS_Connector-0.0.dist-info/WHEEL
Elasticsearch_to_GCS_Connector-0.0.dist-info/entry_points.txt
Elasticsearch_to_GCS_Connector-0.0.dist-info/top_level.txt
Elasticsearch_to_GCS_Connector-0.0.dist-info/RECORD
