Metadata-Version: 2.1
Name: Elasticsearch-to-GCS-Connector
Version: 0.0
Requires-Dist: elasticsearch
Requires-Dist: google-cloud-storage
Requires-Dist: pandas
